Translator/__init__.py
Translator/deu_tokenizer.pickle
Translator/eng_tokenizer.pickle
Translator/translator.py
Translator/ui.py
Translator/arpanKaModel/keras_metadata.pb
Translator/arpanKaModel/saved_model.pb
Translator/arpanKaModel/variables/variables.data-00000-of-00001
Translator/arpanKaModel/variables/variables.index
Ubersetzer-0.0.7.dist-info/LICENCE
Ubersetzer-0.0.7.dist-info/METADATA
Ubersetzer-0.0.7.dist-info/WHEEL
Ubersetzer-0.0.7.dist-info/top_level.txt
Ubersetzer-0.0.7.dist-info/RECORD
