Metadata-Version: 2.1
Name: Ubersetzer
Version: 0.0.7
Summary: For translating German to English
Home-page: UNKNOWN
Author: Arpan Dhamelia
Author-email: arpan110801@gmail.com
License: UNKNOWN
Platform: UNKNOWN
Classifier: Programming Language :: Python :: 3
Classifier: License :: OSI Approved :: MIT License
Classifier: Operating System :: OS Independent
Requires-Python: >=3.7
License-File: LICENCE
